{
    "products": [{
            "id": 1,
            "name": "Cafe americano",
            "price": 8,
            "image": "../../assets/images/cafe_americano.jpg",
            "type": "cafes",
            "dateEntry": "21/01/2022 09:24:00"
        },
        {
            "id": 2,
            "name": "Café con leche",
            "price": 15,
            "image": "../../assets/images/cafe_leche.jpg",
            "type": "cafes",
            "dateEntry": "21/01/2022 09:24:00"
        },
        {
            "id": 3,
            "name": "Sandwich de jamón y queso",
            "price": 10,
            "image": "../../assets/images/Sandwich de jamon y queso.jpg",
            "type": "hamburguers",
            "dateEntry": "21/01/2022 09:24:00"
        },
        {
            "id": 4,
            "name": "Jugo de frutas natural",
            "price": 12,
            "image": "../../assets/images/Jugo de frutas natural.jpg",
            "type": "juices",
            "dateEntry": "21/01/2022 09:24:00"
        },
        {
            "id": 5,
            "name": "Jugo de fresa",
            "price": 12,
            "image": "../../assets/images/Jugo de frutas natural.jpg",
            "type": "juices",
            "dateEntry": "21/01/2022 09:24:00"
        },
        {
            "id": 6,
            "name": "Hamburguesa simple",
            "price": 18,
            "image": "../../assets/images/Hamburguesas.jpg",
            "type": "hamburguers",
            "dateEntry": "21/01/2022 09:24:00"
        },
        {
            "id": 7,
            "name": "Hamburguesa doble",
            "price": 18,
            "image": "../../assets/images/Hamburguesas doble.jpg",
            "type": "hamburguers",
            "dateEntry": "21/01/2022 09:24:00"
        },
        {
            "id": 8,
            "name": "Agua 500ml",
            "price": 18,
            "image": "../../assets/images/Agua 500ml.jpg",
            "type": "drinks",
            "dateEntry": "21/01/2022 09:24:00"
        },
        {
            "id": 9,
            "name": "Agua 750ml",
            "price": 18,
            "image": "../../assets/images/Agua 750ml.jpg",
            "type": "drinks",
            "dateEntry": "21/01/2022 09:24:00"
        },
        {
            "id": 10,
            "name": "Bebida gaseosa 500ml",
            "price": 18,
            "image": "../../assets/images/Bebida gaseosa 500ml.jpg",
            "type": "drinks",
            "dateEntry": "21/01/2022 09:24:00"
        },
        {
          "id": 11,
          "name": "Brownie(unidad)",
          "price": 6,
          "image": "../../assets/images/brownie.png",
          "type": "desserts",
          "dateEntry": "21/01/2022 09:24:00"
        },
        {
          "id": 12,
          "name": "Torta Helada(porción)",
          "price": 7,
          "image": "../../assets/images/tortaHelada.png",
          "type": "desserts",
          "dateEntry": "21/01/2022 09:24:00"
        },
        {
          "id": 13,
          "name": "Helado de lúcuma",
          "price": 4,
          "image": "../../assets/images/helado-de-lucuma.jpg",
          "type": "desserts",
          "dateEntry": "21/01/2022 09:24:00"
        },
        {
          "id": 14,
          "name": "Helado de vainilla",
          "price": 4,
          "image": "../../assets/images/helado-de-vainilla.png",
          "type": "desserts",
          "dateEntry": "21/01/2022 09:24:00"
        },
        {
          "id": 15,
          "name": "Helado de chocolate",
          "price": 4,
          "image": "../../assets/images/helado-de-chocolate.jpg",
          "type": "desserts",
          "dateEntry": "21/01/2022 09:24:00"
        },
        {
          "id": 16,
          "name": "Helado de fresa",
          "price": 4,
          "image": "../../assets/images/helado-de-fresa.png",
          "type": "desserts",
          "dateEntry": "21/01/2022 09:24:00"
        },
        {
          "id": 17,
          "name": "Keke de zanahoria(porción)",
          "price": 8,
          "image": "../../assets/images/keke-de-zanahoria.png",
          "type": "desserts",
          "dateEntry": "21/01/2022 09:24:00"
        },
        {
          "id": 18,
          "name": "Crema volteada(porción)",
          "price": 7,
          "image": "../../assets/images/crema-volteada.png",
          "type": "desserts",
          "dateEntry": "21/01/2022 09:24:00"
        },
        {
          "id": 19,
          "name": "Keke de plátano(porción)",
          "price": 8,
          "image": "../../assets/images/keke-de-platano.jpg",
          "type": "desserts",
          "dateEntry": "21/01/2022 09:24:00"
        },
        {
          "id": 20,
          "name": "Alfajores(unidad)",
          "price": 3.5,
          "image": "../../assets/images/alfajores.png",
          "type": "desserts",
          "dateEntry": "21/01/2022 09:24:00"
        },
        {
          "id": 21,
          "name": "Papas Fritas",
          "price": 12,
          "image": "../../assets/images/Papas fritas.jpg",
          "type": "snacks",
          "dateEntry": "21/01/2022 09:24:00"
        },
        {
          "id": 22,
          "name": "Camotes Fritos",
          "price": 15,
          "image": "../../assets/images/camotes-fritos.jpg",
          "type": "snacks",
          "dateEntry": "21/01/2022 09:24:00"
        },
        {
          "id": 23,
          "name": "Yucas Fritas",
          "price": 15,
          "image": "../../assets/images/yucas-fritas.png",
          "type": "snacks",
          "dateEntry": "21/01/2022 09:24:00"
        },
        {
          "id": 24,
          "name": "Frutos Secos",
          "price": 10,
          "image": "../../assets/images/frutos-secos.jpg",
          "type": "snacks",
          "dateEntry": "21/01/2022 09:24:00"
        },
        {
          "id": 25,
          "name": "Maní Salado",
          "price": 4,
          "image": "../../assets/images/mani-salado.jpg",
          "type": "snacks",
          "dateEntry": "21/01/2022 09:24:00"
        },
        {
          "id": 26,
          "name": "Maní confitado",
          "price": 4,
          "image": "../../assets/images/mani-confitado.jpg",
          "type": "snacks",
          "dateEntry": "21/01/2022 09:24:00"
        },
        {
          "id": 27,
          "name": "Empanada de carne",
          "price": 6,
          "image": "../../assets/images/empanada-de-carne.jpg",
          "type": "snacks",
          "dateEntry": "21/01/2022 09:24:00"
        },
        {
          "id": 28,
          "name": "Empanada de pollo",
          "price": 6,
          "image": "../../assets/images/empanada-de-pollo.jpg",
          "type": "snacks",
          "dateEntry": "21/01/2022 09:24:00"
        },
        {
          "id": 29,
          "name": "Tequeños",
          "price": 8,
          "image": "../../assets/images/tequeños.jpg",
          "type": "snacks",
          "dateEntry": "21/01/2022 09:24:00"
        },
        {
          "id": 30,
          "name": "Granola",
          "price": 6,
          "image": "../../assets/images/granola.jpg",
          "type": "snacks",
          "dateEntry": "21/01/2022 09:24:00"
        }

    ],
    "auth": [{
        "email": "maria@gmail.com",
        "password": "maria"
    },
    {
      "email": "paco@gmail.com",
      "password": "paco"

  },
  {
    "email": "manu@gmail.com",
    "password": "manu"

}
  ],
    "users": [{
            "id": "1",
            "email": "maria@gmail.com",
            "password": "maria",
            "roles": {
                "admin": true,
                "cook": false,
                "waiter": false
            }
        },
        {
            "id": "2",
            "email": "paco@gmail.com",
            "password": "paco",
            "roles": {
                "admin": false,
                "cook": true,
                "waiter": false
            }
        },
        {
            "id": "3",
            "email": "manu@gmail.com",
            "password": "manu",
            "roles": {
                "admin": false,
                "cook": false,
                "waiter": true
            }
        }
    ],
    "order": [{
        "_id": "1",
        "userId": "1",
        "client": "Mili",
        "products": [{
            "id": 2,
            "name": "Café con leche",
            "price": 15,
            "image": "../../src/assets/images/cafe_leche.jpg",
            "type": "desayuno",
            "dateEntry": "21/01/2022 09:24:00"
        }],
        "qty": 2,
        "status": "pending",
        "dateEntry": "21/01/2022 09:24:00",
        "dateProcessed": "21/01/2022 10:00:00"
    }]

}
